dbttools/main.py
dbttools/tasks.py
dbt_tools-0.1.1.dist-info/LICENSE
dbt_tools-0.1.1.dist-info/WHEEL
dbt_tools-0.1.1.dist-info/entry_points.txt
dbt_tools-0.1.1.dist-info/METADATA
dbt_tools-0.1.1.dist-info/RECORD
