Metadata-Version: 2.1
Name: dbt-tools
Version: 0.1.1
Summary: Tools for dbt.
Author: Indi Harrington
Author-email: hi@indigo.rocks
Requires-Python: >=3.10,<4.0
Classifier: Programming Language :: Python :: 3
Classifier: Programming Language :: Python :: 3.10
Classifier: Programming Language :: Python :: 3.11
Requires-Dist: dbt-core (>=1.3.1,<2.0.0)
Requires-Dist: gitpython (>=3.1.29,<4.0.0)
Requires-Dist: invoke (>=1.7.3,<2.0.0)
Requires-Dist: networkx (>=2.8.8,<3.0.0)
Requires-Dist: pyvis (>=0.3.1,<0.4.0)
Requires-Dist: rich (>=12.6.0,<13.0.0)
